fuckpip/__init__.py
fuckpip/test.py
fuckpip-1.0.0.dist-info/DESCRIPTION.rst
fuckpip-1.0.0.dist-info/METADATA
fuckpip-1.0.0.dist-info/RECORD
fuckpip-1.0.0.dist-info/WHEEL
fuckpip-1.0.0.dist-info/entry_points.txt
fuckpip-1.0.0.dist-info/metadata.json
fuckpip-1.0.0.dist-info/top_level.txt
