Metadata-Version: 2.0
Name: fuckpip
Version: 1.0.0
Summary: 测试pip安装包
Home-page: https://test.fstljx.com
Author: 2627866800
Author-email: 2627866800@qq.com
License: UNKNOWN
Platform: UNKNOWN
